azstemmer/__init__.py
azstemmer/azwords.txt
azstemmer/enwords.txt
azstemmer/stemmer.py
azstemmer-0.1.0.dist-info/METADATA
azstemmer-0.1.0.dist-info/WHEEL
azstemmer-0.1.0.dist-info/top_level.txt
azstemmer-0.1.0.dist-info/RECORD
