Metadata-Version: 2.2
Name: azstemmer
Version: 0.1.0
Summary: A stemming library for the Azerbaijani language
Author: Nagi Nagiyev
Author-email: naginagiyev03@gmail.com
Classifier: Programming Language :: Python :: 3
Classifier: Operating System :: OS Independent
Requires-Python: >=3.6
Dynamic: author
Dynamic: author-email
Dynamic: classifier
Dynamic: description
Dynamic: description-content-type
Dynamic: requires-python
Dynamic: summary
